MANIFEST.in
README.rst
setup.py
tcptest/__init__.py
tcptest/fluentd.py
tcptest/memcached.py
tcptest/redis.py
tcptest.egg-info/PKG-INFO
tcptest.egg-info/SOURCES.txt
tcptest.egg-info/dependency_links.txt
tcptest.egg-info/top_level.txt