Metadata-Version: 1.1
Name: tcptest
Version: 0.4.0
Summary: Testing TCP program, following the Perl's Test::TCP include memcached and redis test server.
Home-page: http://github.com/nekoya/python-tcptest
Author: Ryo Miyake
Author-email: ryo.studiom@gmail.com
License: MIT
Platform: UNKNOWN
Classifier: Development Status :: 2 - Pre-Alpha
Classifier: Environment :: Web Environment
Classifier: Intended Audience :: Developers
Classifier: License :: OSI Approved :: MIT License
Classifier: Operating System :: OS Independent
Classifier: Programming Language :: Python
Classifier: Programming Language :: Python :: 2.6
Classifier: Programming Language :: Python :: 2.7
Classifier: Topic :: Software Development :: Testing
